[
  {
    "url": "https://www.escapadah.com/tendencias/2026/3/29/cuales-son-las-lineas-de-autobus-mas-economicas-para-viajar-en-semana-santa-36853.html",
    "source": "escapadah.com",
    "title": "¿Cuáles son las líneas de autobús más económicas para viajar en Semana Santa?",
    "author": [
      "Samantha De La Vega"
    ],
    "published_date": "2026-03-29T00:00:00",
    "description": "Comparta este artículo Viajar en Semana Santa en autobús puede ser una experiencia tanto económica como práctica. La alta demanda suele hacer que los precios suban, pero con un poco de planificación es posible recorrer México con un presupuesto ajustado. Vamos a contarte sobre cómo elegir la línea correcta y cuáles son algunas de las más económicas y cómodas del país. Los descuentos por grupo son una excelente forma de ahorrar. Adultos mayores con credencial INAPAM pueden conseguir hasta un 50% menos en sus boletos, mientras que estudiantes y docentes también pueden acceder a rebajas similares mostrando su identificación vigente. La anticipación también es fundamental. Comprar los boletos con varias semanas de antelación es una gran forma de acceder a tarifas preferenciales antes de que suban por la cercanía de las vacaciones. Además, usar plataformas comparadoras como Wanderu o Busbud hará que te sea más fácil localizar la empresa más"
  }
]