[
  {
    "url": "https://latamobility.com/flixbus-presenta-las-macrotendencias-que-estan-redefiniendo-el-transporte-de-pasajeros-a-nivel-global/",
    "source": "latamobility.com",
    "title": "Flixbus presenta las macrotendencias que están redefiniendo el transporte de pasajeros a nivel global",
    "author": [
      "Antonio Vilela"
    ],
    "published_date": "2026-03-09T10:05:00+00:00",
    "description": "En el marco del «Latam Mobility North America 2026«, Carlos Magaña, director general de Flixbus México, ofreció la ponencia titulada «Macrotendencias del transporte de pasajeros«, en la que compartió su visión sobre el estado actual y el futuro de la industria del autotransporte a nivel global. Aprovechando la posición privilegiada de Flixbus como empresa presente en 45 países y líder en el concepto de mobility as a service, Magaña presentó datos reveladores sobre el tamaño del mercado, las tendencias que lo están transformando y los retos específicos que enfrenta México en este ámbito. El keynote, que tuvo lugar en el Auditorio San Pedro del municipio San Pedro, partió de una premisa contundente: el transporte de pasajeros en todo el mundo está en plena transformación, y la velocidad a la que los distintos mercados se adaptan a este cambio marcará la diferencia en su competitividad y sostenibilidad futura. También te puede"
  }
]